{
  "title":"Plot Title",
  "save_path":"~/Desktop",
  "filename":"example_raster2.png",
  "day_height":0.5,
  "base_block_height":1,
  "events": [
    { 
      "name":"event_type_1", 
      "type":"block",
      "color":"#009933AA", 
      "position":0,
      "height":1,
      "blocks":[ 
        ["2012-11-20T09:30:00","2012-11-20T15:00:00"],
        ["2012-11-21T09:30:00","2012-11-21T17:00:00"],
        ["2012-11-22T09:30:00","2012-11-22T12:00:00"],
        ["2012-11-23T09:30:00","2012-11-23T14:00:00"],
        ["2012-11-24T09:30:00","2012-11-24T14:00:00"]
      ]
    },
    {
      "name":"event_type_2",
      "type":"block",      
      "color":"#0033CCAA",  
      "position":0,
      "height":1,
      "blocks":[
        ["2012-11-20T21:00:00","2012-11-21T06:00:00"],
        ["2012-11-21T21:00:00","2012-11-22T08:00:00"],
        ["2012-11-22T21:00:00","2012-11-23T10:00:00"],
        ["2012-11-23T21:00:00","2012-11-24T05:00:00"],
        ["2012-11-24T21:00:00","2012-11-25T09:00:00"]
      ]
    },
    { 
      "name":"event_type_3", 
      "type":"block",
      "color":"#FFFF00AA", 
      "position":-0.5,
      "height":0.5,
      "blocks":[ 
        ["2012-11-20T11:30:00","2012-11-20T15:00:00"],
        ["2012-11-21T11:30:00","2012-11-21T17:00:00"],
        ["2012-11-22T11:30:00","2012-11-22T12:00:00"],
        ["2012-11-23T11:30:00","2012-11-23T14:00:00"],
        ["2012-11-24T11:30:00","2012-11-24T14:00:00"]
      ]
    },
    {
      "name":"event_type_4",
      "type":"block",
      "color":"#000000AA",  
      "position":-1,
      "height":0.5,
      "blocks":[
        ["2012-11-20T21:00:00","2012-11-21T06:00:00"],
        ["2012-11-21T21:00:00","2012-11-22T08:00:00"],
        ["2012-11-22T21:00:00","2012-11-23T10:00:00"],
        ["2012-11-23T21:00:00","2012-11-24T05:00:00"],
        ["2012-11-24T21:00:00","2012-11-25T09:00:00"]
      ]
    }
  ]
}